README.md
setup.py
nguyenTo/__init__.py
nguyenTo/kiemTraNguyenTo.py
nguyenTo.egg-info/PKG-INFO
nguyenTo.egg-info/SOURCES.txt
nguyenTo.egg-info/dependency_links.txt
nguyenTo.egg-info/top_level.txt