Metadata-Version: 2.1
Name: nguyenTo
Version: 0.0.0
Summary: python cho toán
Author: quanzui
Author-email: <quan06122003@gmail.com>
Keywords: python,toán,prime
Classifier: Development Status :: 1 - Planning
Classifier: Intended Audience :: Developers
Classifier: Programming Language :: Python :: 3
Classifier: Operating System :: POSIX :: Linux
Classifier: Operating System :: MacOS :: MacOS X
Classifier: Operating System :: Microsoft :: Windows
